README.md
manage.py
setup.cfg
setup.py
OpenRoute.egg-info/PKG-INFO
OpenRoute.egg-info/SOURCES.txt
OpenRoute.egg-info/dependency_links.txt
OpenRoute.egg-info/entry_points.txt
OpenRoute.egg-info/requires.txt
OpenRoute.egg-info/top_level.txt
openroute/__init__.py
openroute/geofence.py
openroute/grouping.py
openroute/models.py
openroute/optimize.py
openroute/optimize_alpha.py
openroute/optimize_wave.py
tests/__init__.py
tests/data.py
tests/test_driver_location_grouping.py
tests/test_optimizer.py